scrape_files/__init__.py
scrape_files/args.py
scrape_files/log.py
scrape_files/main.py
scrape_files/progressbar.py
scrape_files-0.2.0.dist-info/entry_points.txt
scrape_files-0.2.0.dist-info/LICENSE
scrape_files-0.2.0.dist-info/WHEEL
scrape_files-0.2.0.dist-info/METADATA
scrape_files-0.2.0.dist-info/RECORD
