Metadata-Version: 2.1
Name: scrape_files
Version: 0.2.0
Summary: `scrape_files` is a tool to help scrape things online to your local machine.
Home-page: https://github.com/mhwgoo/scrape_files
Keywords: python, scraping, html, markdown, image, downloader
Author: Kate Wang
Author-email: kate.wang2018@gmail.com
Requires-Python: >=3.7
Classifier: License :: OSI Approved :: MIT License
Requires-Dist: lxml
Requires-Dist: fake_user_agent
Requires-Dist: requests
